django_ip-1.0.2.dist-info/DESCRIPTION.rst
django_ip-1.0.2.dist-info/METADATA
django_ip-1.0.2.dist-info/RECORD
django_ip-1.0.2.dist-info/WHEEL
django_ip-1.0.2.dist-info/metadata.json
django_ip-1.0.2.dist-info/top_level.txt
ipaddr/__init__.py
ipaddr/clientip.py
ipaddr/decorator.py
ipaddr/middleware.py
